multilevelcli/__init__.py
multilevelcli-0.0.2.dist-info/LICENSE
multilevelcli-0.0.2.dist-info/METADATA
multilevelcli-0.0.2.dist-info/WHEEL
multilevelcli-0.0.2.dist-info/top_level.txt
multilevelcli-0.0.2.dist-info/RECORD
