Metadata-Version: 2.1
Name: multilevelcli
Version: 0.0.2
Summary: A CLI parsing system for multi level CLI ('Cisco like CLI')
Home-page: https://github.com/shaharfrank/multilevelcli
Author: Shahar Frank
Author-email: shahar.frank@example.com
License: UNKNOWN
Platform: UNKNOWN
Classifier: Programming Language :: Python :: 3
Classifier: License :: OSI Approved :: MIT License
Classifier: Operating System :: OS Independent
